Metadata-Version: 1.0
Name: pynstagram
Version: 0.2.0
Summary: simple instagram api
Home-page: https://github.com/OpenJarbas/pynstagram
Author: jarbasAI
Author-email: jarbasai@mailfence.com
License: Apache2
Platform: UNKNOWN
